MANIFEST.in
electronic_mail.xml
setup.py
./__init__.py
./electronic_mail.py
./electronic_mail.xml
./tryton.cfg
./tests/__init__.py
./tests/test_electronic_mail.py
trytond_electronic_mail.egg-info/PKG-INFO
trytond_electronic_mail.egg-info/SOURCES.txt
trytond_electronic_mail.egg-info/dependency_links.txt
trytond_electronic_mail.egg-info/entry_points.txt
trytond_electronic_mail.egg-info/not-zip-safe
trytond_electronic_mail.egg-info/requires.txt
trytond_electronic_mail.egg-info/top_level.txt